ooipy/__init__.py
ooipy/version.py
ooipy/ctd/__init__.py
ooipy/ctd/basic.py
ooipy/hydrophone/__init__.py
ooipy/hydrophone/basic.py
ooipy/hydrophone/calibration_by_assetID.csv
ooipy/request/__init__.py
ooipy/request/authentification.py
ooipy/request/ctd_request.py
ooipy/request/hydrophone_request.py
ooipy/scripts/__init__.py
ooipy/scripts/download_hydrophone_data.py
ooipy/surface_buoy/__init__.py
ooipy/tools/__init__.py
ooipy/tools/ooiplotlib.py
ooipy-1.2.5.dist-info/METADATA
ooipy-1.2.5.dist-info/WHEEL
ooipy-1.2.5.dist-info/entry_points.txt
ooipy-1.2.5.dist-info/licenses/LICENSE
ooipy-1.2.5.dist-info/RECORD
