Metadata-Version: 2.4
Name: ooipy
Version: 1.2.5
Summary: toolbox for downloading and analyzing OOI hydrophone data
Project-URL: Documentation, https://ooipy.readthedocs.io
Project-URL: Issues, https://github.com/Ocean-Data-Lab/ooipy/issues
Project-URL: Source, https://github.com/Ocean-Data-Lab/ooipy
Maintainer-email: John Ragland <jhrag@uw.edu>
License-Expression: MIT
License-File: LICENSE
Classifier: Development Status :: 4 - Beta
Classifier: Programming Language :: Python
Classifier: Programming Language :: Python :: 3.8
Classifier: Programming Language :: Python :: 3.9
Classifier: Programming Language :: Python :: 3.10
Classifier: Programming Language :: Python :: 3.11
Classifier: Programming Language :: Python :: 3.12
Classifier: Programming Language :: Python :: Implementation :: CPython
Classifier: Programming Language :: Python :: Implementation :: PyPy
Requires-Python: >=3.8
Requires-Dist: aiohttp
Requires-Dist: fsspec
Requires-Dist: netcdf4
Requires-Dist: numpy
Requires-Dist: obspy
Requires-Dist: pandas
Requires-Dist: tqdm
Requires-Dist: xarray
Provides-Extra: dev
Requires-Dist: black; extra == 'dev'
Requires-Dist: pre-commit; extra == 'dev'
Provides-Extra: docs
Requires-Dist: furo; extra == 'docs'
Requires-Dist: myst-parser>=0.13; extra == 'docs'
Requires-Dist: sphinx-autodoc-typehints; extra == 'docs'
Requires-Dist: sphinx-copybutton; extra == 'docs'
Requires-Dist: sphinx>=4.0; extra == 'docs'
Requires-Dist: sphinxcontrib-bibtex; extra == 'docs'
Provides-Extra: test
Requires-Dist: pytest>=6.0; extra == 'test'
